{
  "id": "bevan",
  "family": "Bevan",
  "variants": [
    {
      "id": "regular",
      "woff": "https://fonts.gstatic.com/s/bevan/v12/4iCj6KZ0a9NXjG8SWC0.woff",
      "fontFamily": "'Bevan'",
      "fontStyle": "normal",
      "fontWeight": "400",
      "local": [
        "Bevan Regular",
        "Bevan-Regular"
      ],
      "eot": "https://fonts.gstatic.com/s/bevan/v12/4iCj6KZ0a9NXjG8SWC8.eot",
      "woff2": "https://fonts.gstatic.com/s/bevan/v12/4iCj6KZ0a9NXjG8SWCs.woff2",
      "svg": "https://fonts.gstatic.com/l/font?kit=4iCj6KZ0a9NXjG8SWCw&skey=7503fb07de04c1e8&v=v12#Bevan",
      "ttf": "https://fonts.gstatic.com/s/bevan/v12/4iCj6KZ0a9NXjG8SWC4.ttf",
      "errored": false
    }
  ],
  "subsets": [
    "latin",
    "latin-ext",
    "vietnamese"
  ],
  "category": "display",
  "version": "v12",
  "lastModified": "2020-09-02",
  "popularity": 353,
  "defSubset": "latin",
  "defVariant": "regular",
  "subsetMap": {
    "latin": true,
    "latin-ext": false,
    "vietnamese": true
  },
  "storeID": "vietnamese_latin"
}