{
  "id": "pridi",
  "family": "Pridi",
  "variants": [
    {
      "id": "200",
      "woff2": "https://fonts.gstatic.com/s/pridi/v6/2sDdZG5JnZLfkc1SiH0wT0A.woff2",
      "fontFamily": "'Pridi'",
      "fontStyle": "normal",
      "fontWeight": "200",
      "local": [
        "Pridi ExtraLight",
        "Pridi-ExtraLight"
      ],
      "woff": "https://fonts.gstatic.com/s/pridi/v6/2sDdZG5JnZLfkc1SiH0wT0Y.woff",
      "eot": "https://fonts.gstatic.com/s/pridi/v6/2sDdZG5JnZLfkc1SiH0wT0Q.eot",
      "ttf": "https://fonts.gstatic.com/s/pridi/v6/2sDdZG5JnZLfkc1SiH0wT0U.ttf",
      "svg": "https://fonts.gstatic.com/l/font?kit=2sDdZG5JnZLfkc1SiH0wT0c&skey=6defbaa5424aa26a&v=v6#Pridi",
      "errored": false
    },
    {
      "id": "300",
      "eot": "https://fonts.gstatic.com/s/pridi/v6/2sDdZG5JnZLfkc02i30wT0Q.eot",
      "fontFamily": "'Pridi'",
      "fontStyle": "normal",
      "fontWeight": "300",
      "woff": "https://fonts.gstatic.com/s/pridi/v6/2sDdZG5JnZLfkc02i30wT0Y.woff",
      "local": [
        "Pridi Light",
        "Pridi-Light"
      ],
      "svg": "https://fonts.gstatic.com/l/font?kit=2sDdZG5JnZLfkc02i30wT0c&skey=561533c817801d75&v=v6#Pridi",
      "woff2": "https://fonts.gstatic.com/s/pridi/v6/2sDdZG5JnZLfkc02i30wT0A.woff2",
      "ttf": "https://fonts.gstatic.com/s/pridi/v6/2sDdZG5JnZLfkc02i30wT0U.ttf",
      "errored": false
    },
    {
      "id": "regular",
      "eot": "https://fonts.gstatic.com/s/pridi/v6/2sDQZG5JnZLfkcWJqWw.eot",
      "fontFamily": "'Pridi'",
      "fontStyle": "normal",
      "fontWeight": "400",
      "woff": "https://fonts.gstatic.com/s/pridi/v6/2sDQZG5JnZLfkcWJqW4.woff",
      "local": [
        "Pridi Regular",
        "Pridi-Regular"
      ],
      "ttf": "https://fonts.gstatic.com/s/pridi/v6/2sDQZG5JnZLfkcWJqW0.ttf",
      "woff2": "https://fonts.gstatic.com/s/pridi/v6/2sDQZG5JnZLfkcWJqWg.woff2",
      "svg": "https://fonts.gstatic.com/l/font?kit=2sDQZG5JnZLfkcWJqW8&skey=43d1c43aae7d1f74&v=v6#Pridi",
      "errored": false
    },
    {
      "id": "500",
      "eot": "https://fonts.gstatic.com/s/pridi/v6/2sDdZG5JnZLfkc1uin0wT0Q.eot",
      "fontFamily": "'Pridi'",
      "fontStyle": "normal",
      "fontWeight": "500",
      "ttf": "https://fonts.gstatic.com/s/pridi/v6/2sDdZG5JnZLfkc1uin0wT0U.ttf",
      "local": [
        "Pridi Medium",
        "Pridi-Medium"
      ],
      "woff": "https://fonts.gstatic.com/s/pridi/v6/2sDdZG5JnZLfkc1uin0wT0Y.woff",
      "woff2": "https://fonts.gstatic.com/s/pridi/v6/2sDdZG5JnZLfkc1uin0wT0A.woff2",
      "svg": "https://fonts.gstatic.com/l/font?kit=2sDdZG5JnZLfkc1uin0wT0c&skey=e6f379d2c1843a2c&v=v6#Pridi",
      "errored": false
    },
    {
      "id": "600",
      "eot": "https://fonts.gstatic.com/s/pridi/v6/2sDdZG5JnZLfkc1CjX0wT0Q.eot",
      "fontFamily": "'Pridi'",
      "fontStyle": "normal",
      "fontWeight": "600",
      "woff": "https://fonts.gstatic.com/s/pridi/v6/2sDdZG5JnZLfkc1CjX0wT0Y.woff",
      "local": [
        "Pridi SemiBold",
        "Pridi-SemiBold"
      ],
      "svg": "https://fonts.gstatic.com/l/font?kit=2sDdZG5JnZLfkc1CjX0wT0c&skey=b825c36542fbd3d3&v=v6#Pridi",
      "ttf": "https://fonts.gstatic.com/s/pridi/v6/2sDdZG5JnZLfkc1CjX0wT0U.ttf",
      "woff2": "https://fonts.gstatic.com/s/pridi/v6/2sDdZG5JnZLfkc1CjX0wT0A.woff2",
      "errored": false
    },
    {
      "id": "700",
      "eot": "https://fonts.gstatic.com/s/pridi/v6/2sDdZG5JnZLfkc0mjH0wT0Q.eot",
      "fontFamily": "'Pridi'",
      "fontStyle": "normal",
      "fontWeight": "700",
      "woff": "https://fonts.gstatic.com/s/pridi/v6/2sDdZG5JnZLfkc0mjH0wT0Y.woff",
      "local": [
        "Pridi Bold",
        "Pridi-Bold"
      ],
      "woff2": "https://fonts.gstatic.com/s/pridi/v6/2sDdZG5JnZLfkc0mjH0wT0A.woff2",
      "ttf": "https://fonts.gstatic.com/s/pridi/v6/2sDdZG5JnZLfkc0mjH0wT0U.ttf",
      "svg": "https://fonts.gstatic.com/l/font?kit=2sDdZG5JnZLfkc0mjH0wT0c&skey=8dbedb040627946f&v=v6#Pridi",
      "errored": false
    }
  ],
  "subsets": [
    "latin",
    "latin-ext",
    "thai",
    "vietnamese"
  ],
  "category": "serif",
  "version": "v6",
  "lastModified": "2020-09-02",
  "popularity": 242,
  "defSubset": "latin",
  "defVariant": "regular",
  "subsetMap": {
    "latin": true,
    "latin-ext": false,
    "thai": true,
    "vietnamese": false
  },
  "storeID": "thai_latin"
}