{
  "id": "yantramanav",
  "family": "Yantramanav",
  "variants": [
    {
      "id": "100",
      "woff": "https://fonts.gstatic.com/s/yantramanav/v5/flU-Rqu5zY00QEpyWJYWN5-Qbep5Cw.woff",
      "fontFamily": "'Yantramanav'",
      "fontStyle": "normal",
      "fontWeight": "100",
      "local": [
        "Yantramanav Thin",
        "Yantramanav-Thin"
      ],
      "woff2": "https://fonts.gstatic.com/s/yantramanav/v5/flU-Rqu5zY00QEpyWJYWN5-Qbep5DQ.woff2",
      "svg": "https://fonts.gstatic.com/l/font?kit=flU-Rqu5zY00QEpyWJYWN5-Qbep5Cg&skey=4d8237ae265bcb5&v=v5#Yantramanav",
      "ttf": "https://fonts.gstatic.com/s/yantramanav/v5/flU-Rqu5zY00QEpyWJYWN5-Qbep5CA.ttf",
      "eot": "https://fonts.gstatic.com/s/yantramanav/v5/flU-Rqu5zY00QEpyWJYWN5-Qbep5CQ.eot",
      "errored": false
    },
    {
      "id": "regular",
      "eot": "https://fonts.gstatic.com/s/yantramanav/v5/flU8Rqu5zY00QEpyWJYWN5f9XeI.eot",
      "fontFamily": "'Yantramanav'",
      "fontStyle": "normal",
      "fontWeight": "400",
      "woff2": "https://fonts.gstatic.com/s/yantramanav/v5/flU8Rqu5zY00QEpyWJYWN5f9XeY.woff2",
      "local": [
        "Yantramanav Regular",
        "Yantramanav-Regular"
      ],
      "woff": "https://fonts.gstatic.com/s/yantramanav/v5/flU8Rqu5zY00QEpyWJYWN5f9XeA.woff",
      "ttf": "https://fonts.gstatic.com/s/yantramanav/v5/flU8Rqu5zY00QEpyWJYWN5f9XeM.ttf",
      "svg": "https://fonts.gstatic.com/l/font?kit=flU8Rqu5zY00QEpyWJYWN5f9XeE&skey=d721e4e4fbd1e850&v=v5#Yantramanav",
      "errored": false
    },
    {
      "id": "300",
      "woff2": "https://fonts.gstatic.com/s/yantramanav/v5/flUhRqu5zY00QEpyWJYWN59Yf_NQKBM.woff2",
      "fontFamily": "'Yantramanav'",
      "fontStyle": "normal",
      "fontWeight": "300",
      "local": [
        "Yantramanav Light",
        "Yantramanav-Light"
      ],
      "woff": "https://fonts.gstatic.com/s/yantramanav/v5/flUhRqu5zY00QEpyWJYWN59Yf_NQKBU.woff",
      "svg": "https://fonts.gstatic.com/l/font?kit=flUhRqu5zY00QEpyWJYWN59Yf_NQKBQ&skey=4fb8a5ec5d9364f0&v=v5#Yantramanav",
      "ttf": "https://fonts.gstatic.com/s/yantramanav/v5/flUhRqu5zY00QEpyWJYWN59Yf_NQKBY.ttf",
      "eot": "https://fonts.gstatic.com/s/yantramanav/v5/flUhRqu5zY00QEpyWJYWN59Yf_NQKBc.eot",
      "errored": false
    },
    {
      "id": "500",
      "eot": "https://fonts.gstatic.com/s/yantramanav/v5/flUhRqu5zY00QEpyWJYWN58AfvNQKBc.eot",
      "fontFamily": "'Yantramanav'",
      "fontStyle": "normal",
      "fontWeight": "500",
      "woff": "https://fonts.gstatic.com/s/yantramanav/v5/flUhRqu5zY00QEpyWJYWN58AfvNQKBU.woff",
      "local": [
        "Yantramanav Medium",
        "Yantramanav-Medium"
      ],
      "woff2": "https://fonts.gstatic.com/s/yantramanav/v5/flUhRqu5zY00QEpyWJYWN58AfvNQKBM.woff2",
      "svg": "https://fonts.gstatic.com/l/font?kit=flUhRqu5zY00QEpyWJYWN58AfvNQKBQ&skey=ae25c44df595cf2d&v=v5#Yantramanav",
      "ttf": "https://fonts.gstatic.com/s/yantramanav/v5/flUhRqu5zY00QEpyWJYWN58AfvNQKBY.ttf",
      "errored": false
    },
    {
      "id": "700",
      "eot": "https://fonts.gstatic.com/s/yantramanav/v5/flUhRqu5zY00QEpyWJYWN59IePNQKBc.eot",
      "fontFamily": "'Yantramanav'",
      "fontStyle": "normal",
      "fontWeight": "700",
      "woff2": "https://fonts.gstatic.com/s/yantramanav/v5/flUhRqu5zY00QEpyWJYWN59IePNQKBM.woff2",
      "local": [
        "Yantramanav Bold",
        "Yantramanav-Bold"
      ],
      "woff": "https://fonts.gstatic.com/s/yantramanav/v5/flUhRqu5zY00QEpyWJYWN59IePNQKBU.woff",
      "svg": "https://fonts.gstatic.com/l/font?kit=flUhRqu5zY00QEpyWJYWN59IePNQKBQ&skey=35b397cfb7a17297&v=v5#Yantramanav",
      "ttf": "https://fonts.gstatic.com/s/yantramanav/v5/flUhRqu5zY00QEpyWJYWN59IePNQKBY.ttf",
      "errored": false
    },
    {
      "id": "900",
      "eot": "https://fonts.gstatic.com/s/yantramanav/v5/flUhRqu5zY00QEpyWJYWN59wevNQKBc.eot",
      "fontFamily": "'Yantramanav'",
      "fontStyle": "normal",
      "fontWeight": "900",
      "svg": "https://fonts.gstatic.com/l/font?kit=flUhRqu5zY00QEpyWJYWN59wevNQKBQ&skey=6a026953c40595fa&v=v5#Yantramanav",
      "local": [
        "Yantramanav Black",
        "Yantramanav-Black"
      ],
      "woff": "https://fonts.gstatic.com/s/yantramanav/v5/flUhRqu5zY00QEpyWJYWN59wevNQKBU.woff",
      "woff2": "https://fonts.gstatic.com/s/yantramanav/v5/flUhRqu5zY00QEpyWJYWN59wevNQKBM.woff2",
      "ttf": "https://fonts.gstatic.com/s/yantramanav/v5/flUhRqu5zY00QEpyWJYWN59wevNQKBY.ttf",
      "errored": false
    }
  ],
  "subsets": [
    "latin",
    "devanagari",
    "latin-ext"
  ],
  "category": "sans-serif",
  "version": "v5",
  "lastModified": "2019-07-16",
  "popularity": 172,
  "defSubset": "latin",
  "defVariant": "regular",
  "subsetMap": {
    "latin": true,
    "devanagari": false,
    "latin-ext": true
  },
  "storeID": "latin-ext_latin"
}