{
  "id": "seymour-one",
  "family": "Seymour One",
  "variants": [
    {
      "id": "regular",
      "woff": "https://fonts.gstatic.com/s/seymourone/v7/4iCp6Khla9xbjQpoWGGd0lyPN4c.woff",
      "fontFamily": "'Seymour One'",
      "fontStyle": "normal",
      "fontWeight": "400",
      "local": [
        "Seymour One",
        "SeymourOne"
      ],
      "ttf": "https://fonts.gstatic.com/s/seymourone/v7/4iCp6Khla9xbjQpoWGGd0lyPN4Q.ttf",
      "eot": "https://fonts.gstatic.com/s/seymourone/v7/4iCp6Khla9xbjQpoWGGd0lyPN4U.eot",
      "woff2": "https://fonts.gstatic.com/s/seymourone/v7/4iCp6Khla9xbjQpoWGGd0lyPN4E.woff2",
      "svg": "https://fonts.gstatic.com/l/font?kit=4iCp6Khla9xbjQpoWGGd0lyPN4Y&skey=f9acfe398dc38251&v=v7#SeymourOne",
      "errored": false
    }
  ],
  "subsets": [
    "latin",
    "cyrillic",
    "latin-ext"
  ],
  "category": "sans-serif",
  "version": "v7",
  "lastModified": "2019-07-16",
  "popularity": 885,
  "defSubset": "latin",
  "defVariant": "regular",
  "subsetMap": {
    "latin": true,
    "cyrillic": false,
    "latin-ext": false
  },
  "storeID": "latin"
}