{
  "id": "neuton",
  "family": "Neuton",
  "variants": [
    {
      "id": "200",
      "eot": "https://fonts.gstatic.com/s/neuton/v12/UMBQrPtMoH62xUZKAKkvfQr8.eot",
      "fontFamily": "'Neuton'",
      "fontStyle": "normal",
      "fontWeight": "200",
      "svg": "https://fonts.gstatic.com/l/font?kit=UMBQrPtMoH62xUZKAKkvfQr_&skey=13890a023ea5f0b7&v=v12#Neuton",
      "local": [
        "Neuton ExtraLight",
        "Neuton-ExtraLight"
      ],
      "woff": "https://fonts.gstatic.com/s/neuton/v12/UMBQrPtMoH62xUZKAKkvfQr-.woff",
      "woff2": "https://fonts.gstatic.com/s/neuton/v12/UMBQrPtMoH62xUZKAKkvfQr4.woff2",
      "ttf": "https://fonts.gstatic.com/s/neuton/v12/UMBQrPtMoH62xUZKAKkvfQr9.ttf",
      "errored": false
    },
    {
      "id": "300",
      "woff": "https://fonts.gstatic.com/s/neuton/v12/UMBQrPtMoH62xUZKZKovfQr-.woff",
      "fontFamily": "'Neuton'",
      "fontStyle": "normal",
      "fontWeight": "300",
      "local": [
        "Neuton Light",
        "Neuton-Light"
      ],
      "ttf": "https://fonts.gstatic.com/s/neuton/v12/UMBQrPtMoH62xUZKZKovfQr9.ttf",
      "woff2": "https://fonts.gstatic.com/s/neuton/v12/UMBQrPtMoH62xUZKZKovfQr4.woff2",
      "eot": "https://fonts.gstatic.com/s/neuton/v12/UMBQrPtMoH62xUZKZKovfQr8.eot",
      "svg": "https://fonts.gstatic.com/l/font?kit=UMBQrPtMoH62xUZKZKovfQr_&skey=56881972de0a6bb6&v=v12#Neuton",
      "errored": false
    },
    {
      "id": "regular",
      "eot": "https://fonts.gstatic.com/s/neuton/v12/UMBTrPtMoH62xUZCz4g-.eot",
      "fontFamily": "'Neuton'",
      "fontStyle": "normal",
      "fontWeight": "400",
      "woff2": "https://fonts.gstatic.com/s/neuton/v12/UMBTrPtMoH62xUZCz4g6.woff2",
      "local": [
        "Neuton Regular",
        "Neuton-Regular"
      ],
      "woff": "https://fonts.gstatic.com/s/neuton/v12/UMBTrPtMoH62xUZCz4g8.woff",
      "svg": "https://fonts.gstatic.com/l/font?kit=UMBTrPtMoH62xUZCz4g9&skey=88f950a540847181&v=v12#Neuton",
      "ttf": "https://fonts.gstatic.com/s/neuton/v12/UMBTrPtMoH62xUZCz4g_.ttf",
      "errored": false
    },
    {
      "id": "italic",
      "eot": "https://fonts.gstatic.com/s/neuton/v12/UMBRrPtMoH62xUZCyrg4Wis.eot",
      "fontFamily": "'Neuton'",
      "fontStyle": "italic",
      "fontWeight": "400",
      "woff2": "https://fonts.gstatic.com/s/neuton/v12/UMBRrPtMoH62xUZCyrg4Wi8.woff2",
      "local": [
        "Neuton Italic",
        "Neuton-Italic"
      ],
      "woff": "https://fonts.gstatic.com/s/neuton/v12/UMBRrPtMoH62xUZCyrg4Wik.woff",
      "svg": "https://fonts.gstatic.com/l/font?kit=UMBRrPtMoH62xUZCyrg4Wig&skey=891dadfcf29cd902&v=v12#Neuton",
      "ttf": "https://fonts.gstatic.com/s/neuton/v12/UMBRrPtMoH62xUZCyrg4Wio.ttf",
      "errored": false
    },
    {
      "id": "700",
      "eot": "https://fonts.gstatic.com/s/neuton/v12/UMBQrPtMoH62xUZKdK0vfQr8.eot",
      "fontFamily": "'Neuton'",
      "fontStyle": "normal",
      "fontWeight": "700",
      "woff": "https://fonts.gstatic.com/s/neuton/v12/UMBQrPtMoH62xUZKdK0vfQr-.woff",
      "local": [
        "Neuton Bold",
        "Neuton-Bold"
      ],
      "woff2": "https://fonts.gstatic.com/s/neuton/v12/UMBQrPtMoH62xUZKdK0vfQr4.woff2",
      "svg": "https://fonts.gstatic.com/l/font?kit=UMBQrPtMoH62xUZKdK0vfQr_&skey=2fa4dd900c5363d8&v=v12#Neuton",
      "ttf": "https://fonts.gstatic.com/s/neuton/v12/UMBQrPtMoH62xUZKdK0vfQr9.ttf",
      "errored": false
    },
    {
      "id": "800",
      "woff": "https://fonts.gstatic.com/s/neuton/v12/UMBQrPtMoH62xUZKaK4vfQr-.woff",
      "fontFamily": "'Neuton'",
      "fontStyle": "normal",
      "fontWeight": "800",
      "local": [
        "Neuton ExtraBold",
        "Neuton-ExtraBold"
      ],
      "svg": "https://fonts.gstatic.com/l/font?kit=UMBQrPtMoH62xUZKaK4vfQr_&skey=e658fa9062cfc891&v=v12#Neuton",
      "eot": "https://fonts.gstatic.com/s/neuton/v12/UMBQrPtMoH62xUZKaK4vfQr8.eot",
      "ttf": "https://fonts.gstatic.com/s/neuton/v12/UMBQrPtMoH62xUZKaK4vfQr9.ttf",
      "woff2": "https://fonts.gstatic.com/s/neuton/v12/UMBQrPtMoH62xUZKaK4vfQr4.woff2",
      "errored": false
    }
  ],
  "subsets": [
    "latin",
    "latin-ext"
  ],
  "category": "serif",
  "version": "v12",
  "lastModified": "2019-07-16",
  "popularity": 162,
  "defSubset": "latin",
  "defVariant": "regular",
  "subsetMap": {
    "latin": true,
    "latin-ext": false
  },
  "storeID": "latin"
}