{
  "id": "nunito",
  "family": "Nunito",
  "variants": [
    {
      "id": "200",
      "woff2": "https://fonts.gstatic.com/s/nunito/v12/XRXW3I6Li01BKofA-seUbuvI.woff2",
      "fontFamily": "'Nunito'",
      "fontStyle": "normal",
      "fontWeight": "200",
      "local": [
        "Nunito ExtraLight",
        "Nunito-ExtraLight"
      ],
      "eot": "https://fonts.gstatic.com/s/nunito/v12/XRXW3I6Li01BKofA-seUbuvM.eot",
      "svg": "https://fonts.gstatic.com/l/font?kit=XRXW3I6Li01BKofA-seUbuvP&skey=8ad0032e0b847aa6&v=v12#Nunito",
      "ttf": "https://fonts.gstatic.com/s/nunito/v12/XRXW3I6Li01BKofA-seUbuvN.ttf",
      "woff": "https://fonts.gstatic.com/s/nunito/v12/XRXW3I6Li01BKofA-seUbuvO.woff",
      "errored": false
    },
    {
      "id": "200italic",
      "ttf": "https://fonts.gstatic.com/s/nunito/v12/XRXQ3I6Li01BKofIMN5MZ9vFUTo.ttf",
      "fontFamily": "'Nunito'",
      "fontStyle": "italic",
      "fontWeight": "200",
      "local": [
        "Nunito ExtraLight Italic",
        "Nunito-ExtraLightItalic"
      ],
      "svg": "https://fonts.gstatic.com/l/font?kit=XRXQ3I6Li01BKofIMN5MZ9vFUTg&skey=68b7a606f25301c9&v=v12#Nunito",
      "eot": "https://fonts.gstatic.com/s/nunito/v12/XRXQ3I6Li01BKofIMN5MZ9vFUTs.eot",
      "woff": "https://fonts.gstatic.com/s/nunito/v12/XRXQ3I6Li01BKofIMN5MZ9vFUTk.woff",
      "woff2": "https://fonts.gstatic.com/s/nunito/v12/XRXQ3I6Li01BKofIMN5MZ9vFUT8.woff2",
      "errored": false
    },
    {
      "id": "300",
      "eot": "https://fonts.gstatic.com/s/nunito/v12/XRXW3I6Li01BKofAnsSUbuvM.eot",
      "fontFamily": "'Nunito'",
      "fontStyle": "normal",
      "fontWeight": "300",
      "woff": "https://fonts.gstatic.com/s/nunito/v12/XRXW3I6Li01BKofAnsSUbuvO.woff",
      "local": [
        "Nunito Light",
        "Nunito-Light"
      ],
      "woff2": "https://fonts.gstatic.com/s/nunito/v12/XRXW3I6Li01BKofAnsSUbuvI.woff2",
      "svg": "https://fonts.gstatic.com/l/font?kit=XRXW3I6Li01BKofAnsSUbuvP&skey=327ea4351017b269&v=v12#Nunito",
      "ttf": "https://fonts.gstatic.com/s/nunito/v12/XRXW3I6Li01BKofAnsSUbuvN.ttf",
      "errored": false
    },
    {
      "id": "300italic",
      "eot": "https://fonts.gstatic.com/s/nunito/v12/XRXQ3I6Li01BKofIMN4oZNvFUTs.eot",
      "fontFamily": "'Nunito'",
      "fontStyle": "italic",
      "fontWeight": "300",
      "woff2": "https://fonts.gstatic.com/s/nunito/v12/XRXQ3I6Li01BKofIMN4oZNvFUT8.woff2",
      "local": [
        "Nunito Light Italic",
        "Nunito-LightItalic"
      ],
      "woff": "https://fonts.gstatic.com/s/nunito/v12/XRXQ3I6Li01BKofIMN4oZNvFUTk.woff",
      "svg": "https://fonts.gstatic.com/l/font?kit=XRXQ3I6Li01BKofIMN4oZNvFUTg&skey=d788ea5e8f746537&v=v12#Nunito",
      "ttf": "https://fonts.gstatic.com/s/nunito/v12/XRXQ3I6Li01BKofIMN4oZNvFUTo.ttf",
      "errored": false
    },
    {
      "id": "regular",
      "svg": "https://fonts.gstatic.com/l/font?kit=XRXV3I6Li01BKofIOuaG&skey=27bb6aa8eea8a5e7&v=v12#Nunito",
      "fontFamily": "'Nunito'",
      "fontStyle": "normal",
      "fontWeight": "400",
      "local": [
        "Nunito Regular",
        "Nunito-Regular"
      ],
      "eot": "https://fonts.gstatic.com/s/nunito/v12/XRXV3I6Li01BKofIOuaF.eot",
      "woff": "https://fonts.gstatic.com/s/nunito/v12/XRXV3I6Li01BKofIOuaH.woff",
      "ttf": "https://fonts.gstatic.com/s/nunito/v12/XRXV3I6Li01BKofIOuaE.ttf",
      "woff2": "https://fonts.gstatic.com/s/nunito/v12/XRXV3I6Li01BKofIOuaB.woff2",
      "errored": false
    },
    {
      "id": "italic",
      "svg": "https://fonts.gstatic.com/l/font?kit=XRXX3I6Li01BKofIMNaMRsk&skey=75768d03a8bfc23a&v=v12#Nunito",
      "fontFamily": "'Nunito'",
      "fontStyle": "italic",
      "fontWeight": "400",
      "local": [
        "Nunito Italic",
        "Nunito-Italic"
      ],
      "woff": "https://fonts.gstatic.com/s/nunito/v12/XRXX3I6Li01BKofIMNaMRsg.woff",
      "ttf": "https://fonts.gstatic.com/s/nunito/v12/XRXX3I6Li01BKofIMNaMRss.ttf",
      "woff2": "https://fonts.gstatic.com/s/nunito/v12/XRXX3I6Li01BKofIMNaMRs4.woff2",
      "eot": "https://fonts.gstatic.com/s/nunito/v12/XRXX3I6Li01BKofIMNaMRso.eot",
      "errored": false
    },
    {
      "id": "600",
      "eot": "https://fonts.gstatic.com/s/nunito/v12/XRXW3I6Li01BKofA6sKUbuvM.eot",
      "fontFamily": "'Nunito'",
      "fontStyle": "normal",
      "fontWeight": "600",
      "woff": "https://fonts.gstatic.com/s/nunito/v12/XRXW3I6Li01BKofA6sKUbuvO.woff",
      "local": [
        "Nunito SemiBold",
        "Nunito-SemiBold"
      ],
      "ttf": "https://fonts.gstatic.com/s/nunito/v12/XRXW3I6Li01BKofA6sKUbuvN.ttf",
      "woff2": "https://fonts.gstatic.com/s/nunito/v12/XRXW3I6Li01BKofA6sKUbuvI.woff2",
      "svg": "https://fonts.gstatic.com/l/font?kit=XRXW3I6Li01BKofA6sKUbuvP&skey=52e177ab83d749aa&v=v12#Nunito",
      "errored": false
    },
    {
      "id": "600italic",
      "woff": "https://fonts.gstatic.com/s/nunito/v12/XRXQ3I6Li01BKofIMN5cYtvFUTk.woff",
      "fontFamily": "'Nunito'",
      "fontStyle": "italic",
      "fontWeight": "600",
      "local": [
        "Nunito SemiBold Italic",
        "Nunito-SemiBoldItalic"
      ],
      "eot": "https://fonts.gstatic.com/s/nunito/v12/XRXQ3I6Li01BKofIMN5cYtvFUTs.eot",
      "ttf": "https://fonts.gstatic.com/s/nunito/v12/XRXQ3I6Li01BKofIMN5cYtvFUTo.ttf",
      "svg": "https://fonts.gstatic.com/l/font?kit=XRXQ3I6Li01BKofIMN5cYtvFUTg&skey=b7a2cf2364e291f2&v=v12#Nunito",
      "woff2": "https://fonts.gstatic.com/s/nunito/v12/XRXQ3I6Li01BKofIMN5cYtvFUT8.woff2",
      "errored": false
    },
    {
      "id": "700",
      "woff2": "https://fonts.gstatic.com/s/nunito/v12/XRXW3I6Li01BKofAjsOUbuvI.woff2",
      "fontFamily": "'Nunito'",
      "fontStyle": "normal",
      "fontWeight": "700",
      "local": [
        "Nunito Bold",
        "Nunito-Bold"
      ],
      "svg": "https://fonts.gstatic.com/l/font?kit=XRXW3I6Li01BKofAjsOUbuvP&skey=388548fee26cf4d3&v=v12#Nunito",
      "eot": "https://fonts.gstatic.com/s/nunito/v12/XRXW3I6Li01BKofAjsOUbuvM.eot",
      "ttf": "https://fonts.gstatic.com/s/nunito/v12/XRXW3I6Li01BKofAjsOUbuvN.ttf",
      "woff": "https://fonts.gstatic.com/s/nunito/v12/XRXW3I6Li01BKofAjsOUbuvO.woff",
      "errored": false
    },
    {
      "id": "700italic",
      "eot": "https://fonts.gstatic.com/s/nunito/v12/XRXQ3I6Li01BKofIMN44Y9vFUTs.eot",
      "fontFamily": "'Nunito'",
      "fontStyle": "italic",
      "fontWeight": "700",
      "woff2": "https://fonts.gstatic.com/s/nunito/v12/XRXQ3I6Li01BKofIMN44Y9vFUT8.woff2",
      "local": [
        "Nunito Bold Italic",
        "Nunito-BoldItalic"
      ],
      "svg": "https://fonts.gstatic.com/l/font?kit=XRXQ3I6Li01BKofIMN44Y9vFUTg&skey=a6fac914b3b6528d&v=v12#Nunito",
      "ttf": "https://fonts.gstatic.com/s/nunito/v12/XRXQ3I6Li01BKofIMN44Y9vFUTo.ttf",
      "woff": "https://fonts.gstatic.com/s/nunito/v12/XRXQ3I6Li01BKofIMN44Y9vFUTk.woff",
      "errored": false
    },
    {
      "id": "800",
      "woff": "https://fonts.gstatic.com/s/nunito/v12/XRXW3I6Li01BKofAksCUbuvO.woff",
      "fontFamily": "'Nunito'",
      "fontStyle": "normal",
      "fontWeight": "800",
      "local": [
        "Nunito ExtraBold",
        "Nunito-ExtraBold"
      ],
      "woff2": "https://fonts.gstatic.com/s/nunito/v12/XRXW3I6Li01BKofAksCUbuvI.woff2",
      "svg": "https://fonts.gstatic.com/l/font?kit=XRXW3I6Li01BKofAksCUbuvP&skey=c2b8d7855f17a8f6&v=v12#Nunito",
      "eot": "https://fonts.gstatic.com/s/nunito/v12/XRXW3I6Li01BKofAksCUbuvM.eot",
      "ttf": "https://fonts.gstatic.com/s/nunito/v12/XRXW3I6Li01BKofAksCUbuvN.ttf",
      "errored": false
    },
    {
      "id": "800italic",
      "eot": "https://fonts.gstatic.com/s/nunito/v12/XRXQ3I6Li01BKofIMN4kYNvFUTs.eot",
      "fontFamily": "'Nunito'",
      "fontStyle": "italic",
      "fontWeight": "800",
      "woff2": "https://fonts.gstatic.com/s/nunito/v12/XRXQ3I6Li01BKofIMN4kYNvFUT8.woff2",
      "local": [
        "Nunito ExtraBold Italic",
        "Nunito-ExtraBoldItalic"
      ],
      "svg": "https://fonts.gstatic.com/l/font?kit=XRXQ3I6Li01BKofIMN4kYNvFUTg&skey=32afafedc6e00101&v=v12#Nunito",
      "woff": "https://fonts.gstatic.com/s/nunito/v12/XRXQ3I6Li01BKofIMN4kYNvFUTk.woff",
      "ttf": "https://fonts.gstatic.com/s/nunito/v12/XRXQ3I6Li01BKofIMN4kYNvFUTo.ttf",
      "errored": false
    },
    {
      "id": "900italic",
      "eot": "https://fonts.gstatic.com/s/nunito/v12/XRXQ3I6Li01BKofIMN4AYdvFUTs.eot",
      "fontFamily": "'Nunito'",
      "fontStyle": "italic",
      "fontWeight": "900",
      "svg": "https://fonts.gstatic.com/l/font?kit=XRXQ3I6Li01BKofIMN4AYdvFUTg&skey=4d145ea69c011471&v=v12#Nunito",
      "local": [
        "Nunito Black Italic",
        "Nunito-BlackItalic"
      ],
      "ttf": "https://fonts.gstatic.com/s/nunito/v12/XRXQ3I6Li01BKofIMN4AYdvFUTo.ttf",
      "woff": "https://fonts.gstatic.com/s/nunito/v12/XRXQ3I6Li01BKofIMN4AYdvFUTk.woff",
      "woff2": "https://fonts.gstatic.com/s/nunito/v12/XRXQ3I6Li01BKofIMN4AYdvFUT8.woff2",
      "errored": false
    },
    {
      "id": "900",
      "woff2": "https://fonts.gstatic.com/s/nunito/v12/XRXW3I6Li01BKofAtsGUbuvI.woff2",
      "fontFamily": "'Nunito'",
      "fontStyle": "normal",
      "fontWeight": "900",
      "local": [
        "Nunito Black",
        "Nunito-Black"
      ],
      "eot": "https://fonts.gstatic.com/s/nunito/v12/XRXW3I6Li01BKofAtsGUbuvM.eot",
      "svg": "https://fonts.gstatic.com/l/font?kit=XRXW3I6Li01BKofAtsGUbuvP&skey=9c07924cc4353e8f&v=v12#Nunito",
      "ttf": "https://fonts.gstatic.com/s/nunito/v12/XRXW3I6Li01BKofAtsGUbuvN.ttf",
      "woff": "https://fonts.gstatic.com/s/nunito/v12/XRXW3I6Li01BKofAtsGUbuvO.woff",
      "errored": false
    }
  ],
  "subsets": [
    "cyrillic-ext",
    "latin-ext",
    "vietnamese",
    "latin",
    "cyrillic"
  ],
  "category": "sans-serif",
  "version": "v12",
  "lastModified": "2019-11-14",
  "popularity": 22,
  "defSubset": "latin",
  "defVariant": "regular",
  "subsetMap": {
    "cyrillic-ext": false,
    "latin-ext": false,
    "vietnamese": true,
    "latin": true,
    "cyrillic": false
  },
  "storeID": "latin_vietnamese"
}