{
  "id": "gabriela",
  "family": "Gabriela",
  "variants": [
    {
      "id": "regular",
      "woff2": "https://fonts.gstatic.com/s/gabriela/v9/qkBWXvsO6sreR8E-b8m0xLs.woff2",
      "fontFamily": "'Gabriela'",
      "fontStyle": "normal",
      "fontWeight": "400",
      "local": [
        "Gabriela Regular",
        "Gabriela-Regular"
      ],
      "eot": "https://fonts.gstatic.com/s/gabriela/v9/qkBWXvsO6sreR8E-b8m0xL8.eot",
      "ttf": "https://fonts.gstatic.com/s/gabriela/v9/qkBWXvsO6sreR8E-b8m0xL4.ttf",
      "woff": "https://fonts.gstatic.com/s/gabriela/v9/qkBWXvsO6sreR8E-b8m0xL0.woff",
      "svg": "https://fonts.gstatic.com/l/font?kit=qkBWXvsO6sreR8E-b8m0xLw&skey=146d0218141ab9a9&v=v9#Gabriela",
      "errored": false
    }
  ],
  "subsets": [
    "cyrillic",
    "cyrillic-ext",
    "latin"
  ],
  "category": "serif",
  "version": "v9",
  "lastModified": "2020-07-23",
  "popularity": 506,
  "defSubset": "latin",
  "defVariant": "regular",
  "subsetMap": {
    "cyrillic": false,
    "cyrillic-ext": true,
    "latin": true
  },
  "storeID": "latin_cyrillic-ext"
}