{
  "id": "noto-sans-tc",
  "family": "Noto Sans TC",
  "variants": [
    {
      "id": "100",
      "woff": "https://fonts.gstatic.com/s/notosanstc/v9/-nFlOG829Oofr2wohFbTp9i9WxEIK_Q.woff",
      "fontFamily": "'Noto Sans TC'",
      "fontStyle": "normal",
      "fontWeight": "100",
      "local": [
        "Noto Sans TC Thin",
        "NotoSansTC-Thin"
      ],
      "svg": "https://fonts.gstatic.com/l/font?kit=-nFlOG829Oofr2wohFbTp9i9WxEIK_U&skey=6d661096809e0eb4&v=v9#NotoSansTC",
      "woff2": "https://fonts.gstatic.com/s/notosanstc/v9/-nFlOG829Oofr2wohFbTp9i9WxEIK_I.woff2",
      "eot": "https://fonts.gstatic.com/s/notosanstc/v9/-nFlOG829Oofr2wohFbTp9i9WxEIK_Y.eot",
      "errored": false
    },
    {
      "id": "300",
      "woff2": "https://fonts.gstatic.com/s/notosanstc/v9/-nFkOG829Oofr2wohFbTp9i9kwMfDNdU.woff2",
      "fontFamily": "'Noto Sans TC'",
      "fontStyle": "normal",
      "fontWeight": "300",
      "local": [
        "Noto Sans TC Light",
        "NotoSansTC-Light"
      ],
      "woff": "https://fonts.gstatic.com/s/notosanstc/v9/-nFkOG829Oofr2wohFbTp9i9kwMfDNdS.woff",
      "svg": "https://fonts.gstatic.com/l/font?kit=-nFkOG829Oofr2wohFbTp9i9kwMfDNdT&skey=4f56a9d9b4fc44ec&v=v9#NotoSansTC",
      "eot": "https://fonts.gstatic.com/s/notosanstc/v9/-nFkOG829Oofr2wohFbTp9i9kwMfDNdQ.eot",
      "errored": false
    },
    {
      "id": "regular",
      "woff": "https://fonts.gstatic.com/s/notosanstc/v9/-nF7OG829Oofr2wohFbTp9i1OCEM.woff",
      "fontFamily": "'Noto Sans TC'",
      "fontStyle": "normal",
      "fontWeight": "400",
      "local": [
        "Noto Sans TC Regular",
        "NotoSansTC-Regular"
      ],
      "svg": "https://fonts.gstatic.com/l/font?kit=-nF7OG829Oofr2wohFbTp9i1OCEN&skey=3904269dc8bdd0a1&v=v9#NotoSansTC",
      "woff2": "https://fonts.gstatic.com/s/notosanstc/v9/-nF7OG829Oofr2wohFbTp9i1OCEK.woff2",
      "eot": "https://fonts.gstatic.com/s/notosanstc/v9/-nF7OG829Oofr2wohFbTp9i1OCEO.eot",
      "errored": false
    },
    {
      "id": "500",
      "eot": "https://fonts.gstatic.com/s/notosanstc/v9/-nFkOG829Oofr2wohFbTp9i9ywIfDNdQ.eot",
      "fontFamily": "'Noto Sans TC'",
      "fontStyle": "normal",
      "fontWeight": "500",
      "woff": "https://fonts.gstatic.com/s/notosanstc/v9/-nFkOG829Oofr2wohFbTp9i9ywIfDNdS.woff",
      "local": [
        "Noto Sans TC Medium",
        "NotoSansTC-Medium"
      ],
      "woff2": "https://fonts.gstatic.com/s/notosanstc/v9/-nFkOG829Oofr2wohFbTp9i9ywIfDNdU.woff2",
      "svg": "https://fonts.gstatic.com/l/font?kit=-nFkOG829Oofr2wohFbTp9i9ywIfDNdT&skey=20fc04d331330da1&v=v9#NotoSansTC",
      "errored": false
    },
    {
      "id": "700",
      "woff": "https://fonts.gstatic.com/s/notosanstc/v9/-nFkOG829Oofr2wohFbTp9i9gwQfDNdS.woff",
      "fontFamily": "'Noto Sans TC'",
      "fontStyle": "normal",
      "fontWeight": "700",
      "local": [
        "Noto Sans TC Bold",
        "NotoSansTC-Bold"
      ],
      "svg": "https://fonts.gstatic.com/l/font?kit=-nFkOG829Oofr2wohFbTp9i9gwQfDNdT&skey=113355c0388222ad&v=v9#NotoSansTC",
      "eot": "https://fonts.gstatic.com/s/notosanstc/v9/-nFkOG829Oofr2wohFbTp9i9gwQfDNdQ.eot",
      "woff2": "https://fonts.gstatic.com/s/notosanstc/v9/-nFkOG829Oofr2wohFbTp9i9gwQfDNdU.woff2",
      "errored": false
    },
    {
      "id": "900",
      "svg": "https://fonts.gstatic.com/l/font?kit=-nFkOG829Oofr2wohFbTp9i9uwYfDNdT&skey=c2a6163ab9045fa0&v=v9#NotoSansTC",
      "fontFamily": "'Noto Sans TC'",
      "fontStyle": "normal",
      "fontWeight": "900",
      "local": [
        "Noto Sans TC Black",
        "NotoSansTC-Black"
      ],
      "woff2": "https://fonts.gstatic.com/s/notosanstc/v9/-nFkOG829Oofr2wohFbTp9i9uwYfDNdU.woff2",
      "eot": "https://fonts.gstatic.com/s/notosanstc/v9/-nFkOG829Oofr2wohFbTp9i9uwYfDNdQ.eot",
      "woff": "https://fonts.gstatic.com/s/notosanstc/v9/-nFkOG829Oofr2wohFbTp9i9uwYfDNdS.woff",
      "errored": false
    }
  ],
  "subsets": [
    "chinese-traditional",
    "latin"
  ],
  "category": "sans-serif",
  "version": "v9",
  "lastModified": "2019-07-17",
  "popularity": 65,
  "defSubset": "latin",
  "defVariant": "regular",
  "subsetMap": {
    "chinese-traditional": false,
    "latin": true
  },
  "storeID": "latin"
}