{
  "id": "baloo-thambi",
  "family": "Baloo Thambi",
  "variants": [
    {
      "id": "regular",
      "woff2": "https://fonts.gstatic.com/s/baloothambi/v5/va9B4kXJzNhTFoA7CYcS8sHeUBf6.woff2",
      "fontFamily": "'Baloo Thambi'",
      "fontStyle": "normal",
      "fontWeight": "400",
      "local": [
        "Baloo Thambi Regular",
        "BalooThambi-Regular"
      ],
      "eot": "https://fonts.gstatic.com/s/baloothambi/v5/va9B4kXJzNhTFoA7CYcS8sHeUBf-.eot",
      "woff": "https://fonts.gstatic.com/s/baloothambi/v5/va9B4kXJzNhTFoA7CYcS8sHeUBf8.woff",
      "svg": "https://fonts.gstatic.com/l/font?kit=va9B4kXJzNhTFoA7CYcS8sHeUBf9&skey=8868b806ee96bb3b&v=v5#BalooThambi",
      "ttf": "https://fonts.gstatic.com/s/baloothambi/v5/va9B4kXJzNhTFoA7CYcS8sHeUBf_.ttf",
      "errored": false
    }
  ],
  "subsets": [
    "vietnamese",
    "latin",
    "latin-ext",
    "tamil"
  ],
  "category": "display",
  "version": "v5",
  "lastModified": "2019-07-16",
  "popularity": 617,
  "defSubset": "latin",
  "defVariant": "regular",
  "subsetMap": {
    "vietnamese": false,
    "latin": true,
    "latin-ext": false,
    "tamil": true
  },
  "storeID": "tamil_latin"
}