{
  "id": "beth-ellen",
  "family": "Beth Ellen",
  "variants": [
    {
      "id": "regular",
      "svg": "https://fonts.gstatic.com/l/font?kit=WwkbxPW2BE-3rb_JNT-qIIcoUg&skey=25b69ed324f5791a&v=v3#BethEllen",
      "fontFamily": "'Beth Ellen'",
      "fontStyle": "normal",
      "fontWeight": "400",
      "local": [
        "Beth Ellen Regular",
        "BethEllen-Regular"
      ],
      "woff2": "https://fonts.gstatic.com/s/bethellen/v3/WwkbxPW2BE-3rb_JNT-qIIcoVQ.woff2",
      "woff": "https://fonts.gstatic.com/s/bethellen/v3/WwkbxPW2BE-3rb_JNT-qIIcoUw.woff",
      "eot": "https://fonts.gstatic.com/s/bethellen/v3/WwkbxPW2BE-3rb_JNT-qIIcoUQ.eot",
      "ttf": "https://fonts.gstatic.com/s/bethellen/v3/WwkbxPW2BE-3rb_JNT-qIIcoUA.ttf",
      "errored": false
    }
  ],
  "subsets": [
    "latin"
  ],
  "category": "handwriting",
  "version": "v3",
  "lastModified": "2020-07-23",
  "popularity": 961,
  "defSubset": "latin",
  "defVariant": "regular",
  "subsetMap": {
    "latin": true
  },
  "storeID": "latin"
}