{
  "id": "news-cycle",
  "family": "News Cycle",
  "variants": [
    {
      "id": "700",
      "svg": "https://fonts.gstatic.com/l/font?kit=CSR54z1Qlv-GDxkbKVQ_dFsvWNRevg&skey=303b508802781511&v=v16#NewsCycle",
      "fontFamily": "'News Cycle'",
      "fontStyle": "normal",
      "fontWeight": "700",
      "local": [
        "News Cycle Bold",
        "NewsCycle-Bold"
      ],
      "woff": "https://fonts.gstatic.com/s/newscycle/v16/CSR54z1Qlv-GDxkbKVQ_dFsvWNRevw.woff",
      "eot": "https://fonts.gstatic.com/s/newscycle/v16/CSR54z1Qlv-GDxkbKVQ_dFsvWNRevQ.eot",
      "woff2": "https://fonts.gstatic.com/s/newscycle/v16/CSR54z1Qlv-GDxkbKVQ_dFsvWNReuQ.woff2",
      "ttf": "https://fonts.gstatic.com/s/newscycle/v16/CSR54z1Qlv-GDxkbKVQ_dFsvWNRevA.ttf",
      "errored": false
    },
    {
      "id": "regular",
      "woff": "https://fonts.gstatic.com/s/newscycle/v16/CSR64z1Qlv-GDxkbKVQ_fOAKSw.woff",
      "fontFamily": "'News Cycle'",
      "fontStyle": "normal",
      "fontWeight": "400",
      "local": [
        "News Cycle",
        "NewsCycle"
      ],
      "woff2": "https://fonts.gstatic.com/s/newscycle/v16/CSR64z1Qlv-GDxkbKVQ_fOAKTQ.woff2",
      "ttf": "https://fonts.gstatic.com/s/newscycle/v16/CSR64z1Qlv-GDxkbKVQ_fOAKSA.ttf",
      "svg": "https://fonts.gstatic.com/l/font?kit=CSR64z1Qlv-GDxkbKVQ_fOAKSg&skey=315d90a3c97443a7&v=v16#NewsCycle",
      "eot": "https://fonts.gstatic.com/s/newscycle/v16/CSR64z1Qlv-GDxkbKVQ_fOAKSQ.eot",
      "errored": false
    }
  ],
  "subsets": [
    "latin",
    "latin-ext"
  ],
  "category": "sans-serif",
  "version": "v16",
  "lastModified": "2019-07-17",
  "popularity": 96,
  "defSubset": "latin",
  "defVariant": "regular",
  "subsetMap": {
    "latin": true,
    "latin-ext": false
  },
  "storeID": "latin"
}