{
  "id": "give-you-glory",
  "family": "Give You Glory",
  "variants": [
    {
      "id": "regular",
      "woff": "https://fonts.gstatic.com/s/giveyouglory/v10/8QIQdiHOgt3vv4LR7ahjw9-XYf10DYE.woff",
      "fontFamily": "'Give You Glory'",
      "fontStyle": "normal",
      "fontWeight": "400",
      "local": [
        "Give You Glory",
        "GiveYouGlory"
      ],
      "eot": "https://fonts.gstatic.com/s/giveyouglory/v10/8QIQdiHOgt3vv4LR7ahjw9-XYf10DYM.eot",
      "ttf": "https://fonts.gstatic.com/s/giveyouglory/v10/8QIQdiHOgt3vv4LR7ahjw9-XYf10DYI.ttf",
      "woff2": "https://fonts.gstatic.com/s/giveyouglory/v10/8QIQdiHOgt3vv4LR7ahjw9-XYf10DYc.woff2",
      "svg": "https://fonts.gstatic.com/l/font?kit=8QIQdiHOgt3vv4LR7ahjw9-XYf10DYA&skey=147545eeeab1069c&v=v10#GiveYouGlory",
      "errored": false
    }
  ],
  "subsets": [
    "latin"
  ],
  "category": "handwriting",
  "version": "v10",
  "lastModified": "2020-07-23",
  "popularity": 601,
  "defSubset": "latin",
  "defVariant": "regular",
  "subsetMap": {
    "latin": true
  },
  "storeID": "latin"
}