{
  "id": "bentham",
  "family": "Bentham",
  "variants": [
    {
      "id": "regular",
      "eot": "https://fonts.gstatic.com/s/bentham/v11/VdGeAZQPEpYfmHglGWsxDQ.eot",
      "fontFamily": "'Bentham'",
      "fontStyle": "normal",
      "fontWeight": "400",
      "ttf": "https://fonts.gstatic.com/s/bentham/v11/VdGeAZQPEpYfmHglGWsxDA.ttf",
      "local": [
        "Bentham Regular",
        "Bentham-Regular"
      ],
      "woff2": "https://fonts.gstatic.com/s/bentham/v11/VdGeAZQPEpYfmHglGWsxCQ.woff2",
      "woff": "https://fonts.gstatic.com/s/bentham/v11/VdGeAZQPEpYfmHglGWsxDw.woff",
      "svg": "https://fonts.gstatic.com/l/font?kit=VdGeAZQPEpYfmHglGWsxDg&skey=65ea27bccb65e6d3&v=v11#Bentham",
      "errored": false
    }
  ],
  "subsets": [
    "latin"
  ],
  "category": "serif",
  "version": "v11",
  "lastModified": "2020-09-02",
  "popularity": 365,
  "defSubset": "latin",
  "defVariant": "regular",
  "subsetMap": {
    "latin": true
  },
  "storeID": "latin"
}