{
  "id": "ropa-sans",
  "family": "Ropa Sans",
  "variants": [
    {
      "id": "regular",
      "woff": "https://fonts.gstatic.com/s/ropasans/v10/EYqxmaNOzLlWtsZSScy6XTNv.woff",
      "fontFamily": "'Ropa Sans'",
      "fontStyle": "normal",
      "fontWeight": "400",
      "local": [
        "Ropa Sans Regular",
        "RopaSans-Regular"
      ],
      "svg": "https://fonts.gstatic.com/l/font?kit=EYqxmaNOzLlWtsZSScy6XTNu&skey=edf65b5a911839ad&v=v10#RopaSans",
      "ttf": "https://fonts.gstatic.com/s/ropasans/v10/EYqxmaNOzLlWtsZSScy6XTNs.ttf",
      "woff2": "https://fonts.gstatic.com/s/ropasans/v10/EYqxmaNOzLlWtsZSScy6XTNp.woff2",
      "eot": "https://fonts.gstatic.com/s/ropasans/v10/EYqxmaNOzLlWtsZSScy6XTNt.eot",
      "errored": false
    },
    {
      "id": "italic",
      "ttf": "https://fonts.gstatic.com/s/ropasans/v10/EYq3maNOzLlWtsZSScy6WANre5M.ttf",
      "fontFamily": "'Ropa Sans'",
      "fontStyle": "italic",
      "fontWeight": "400",
      "local": [
        "Ropa Sans Italic",
        "RopaSans-Italic"
      ],
      "woff2": "https://fonts.gstatic.com/s/ropasans/v10/EYq3maNOzLlWtsZSScy6WANre5Y.woff2",
      "woff": "https://fonts.gstatic.com/s/ropasans/v10/EYq3maNOzLlWtsZSScy6WANre5A.woff",
      "eot": "https://fonts.gstatic.com/s/ropasans/v10/EYq3maNOzLlWtsZSScy6WANre5I.eot",
      "svg": "https://fonts.gstatic.com/l/font?kit=EYq3maNOzLlWtsZSScy6WANre5E&skey=c6198dadd1bf5d82&v=v10#RopaSans",
      "errored": false
    }
  ],
  "subsets": [
    "latin",
    "latin-ext"
  ],
  "category": "sans-serif",
  "version": "v10",
  "lastModified": "2020-09-02",
  "popularity": 162,
  "defSubset": "latin",
  "defVariant": "regular",
  "subsetMap": {
    "latin": true,
    "latin-ext": false
  },
  "storeID": "latin"
}