{
  "id": "gafata",
  "family": "Gafata",
  "variants": [
    {
      "id": "regular",
      "eot": "https://fonts.gstatic.com/s/gafata/v9/XRXV3I6Cn0VJKonINeaF.eot",
      "fontFamily": "'Gafata'",
      "fontStyle": "normal",
      "fontWeight": "400",
      "woff2": "https://fonts.gstatic.com/s/gafata/v9/XRXV3I6Cn0VJKonINeaB.woff2",
      "local": [
        "Gafata",
        "Gafata-Regular"
      ],
      "ttf": "https://fonts.gstatic.com/s/gafata/v9/XRXV3I6Cn0VJKonINeaE.ttf",
      "svg": "https://fonts.gstatic.com/l/font?kit=XRXV3I6Cn0VJKonINeaG&skey=ac32f67a7703448a&v=v9#Gafata",
      "woff": "https://fonts.gstatic.com/s/gafata/v9/XRXV3I6Cn0VJKonINeaH.woff",
      "errored": false
    }
  ],
  "subsets": [
    "latin",
    "latin-ext"
  ],
  "category": "sans-serif",
  "version": "v9",
  "lastModified": "2020-07-23",
  "popularity": 603,
  "defSubset": "latin",
  "defVariant": "regular",
  "subsetMap": {
    "latin": true,
    "latin-ext": false
  },
  "storeID": "latin"
}